psed/__init__.py
psed/__main__.py
psed/logger.py
psed/psed.py
psed-0.1.0.dist-info/AUTHORS.rst
psed-0.1.0.dist-info/LICENSE
psed-0.1.0.dist-info/METADATA
psed-0.1.0.dist-info/PKG-INFO_psed
psed-0.1.0.dist-info/WHEEL
psed-0.1.0.dist-info/entry_points.txt
psed-0.1.0.dist-info/top_level.txt
psed-0.1.0.dist-info/RECORD
