Metadata-Version: 2.1
Name: psed
Version: 0.1.0
Summary: CLI utility for text search / replace.
Home-page: https://github.com/aklajnert/psed
Author: Andrzej Klajnert
Author-email: py@aklajnert.pl
License: MIT license
Keywords: psed
Platform: UNKNOWN
Classifier: Intended Audience :: Developers
Classifier: License :: OSI Approved :: MIT License
Classifier: Operating System :: OS Independent
Classifier: Natural Language :: English
Classifier: Programming Language :: Python :: 3
Classifier: Programming Language :: Python :: 3.6
Classifier: Programming Language :: Python :: 3.7
Classifier: Programming Language :: Python :: 3.8
Requires-Dist: Click (>=7.0)
Provides-Extra: dev
Requires-Dist: tox (==3.12.1) ; extra == 'dev'
Requires-Dist: black (==19.3b0) ; extra == 'dev'
Provides-Extra: test
Requires-Dist: pytest (>=5.1.0) ; extra == 'test'
Requires-Dist: pytest-cov (>=2.7.0) ; extra == 'test'
Requires-Dist: pyfakefs (==3.6) ; extra == 'test'
Requires-Dist: pytest-azurepipelines (==0.8.0) ; extra == 'test'
